hitme.py
hitmeconfig.py
misc.py
setup.py
tufts_grading_assignment_utility-9.20.2024.dist-info/licenses/LICENSE
tufts_grading_assignment_utility-9.20.2024.dist-info/METADATA
tufts_grading_assignment_utility-9.20.2024.dist-info/WHEEL
tufts_grading_assignment_utility-9.20.2024.dist-info/top_level.txt
tufts_grading_assignment_utility-9.20.2024.dist-info/RECORD
