Metadata-Version: 2.4
Name: tufts-grading-assignment-utility
Version: 9.20.2024
Summary: Grading assignment utility known as 'hitme' that is used by Tufts University course COMP 15 staff members. Written from scratch to replace an old variant of the system that works with Gradescope submission data.
Author: Chami Lamelas
License: MIT License
Project-URL: Repository, https://github.com/ChamiLamelas/hitme-grading
Project-URL: Author, https://sites.google.com/view/chami-lamelas
Requires-Python: >=3.9.2
License-File: LICENSE
Requires-Dist: paramiko>=3.4.0
Dynamic: license-file
